LICENSE
MANIFEST.in
README.rst
griddb_python_client.py
setup.cfg
setup.py
griddb_python_client.egg-info/PKG-INFO
griddb_python_client.egg-info/SOURCES.txt
griddb_python_client.egg-info/dependency_links.txt
griddb_python_client.egg-info/top_level.txt
include/gridstore.h
src/AggregationResult.cpp
src/AggregationResult.h
src/Container.cpp
src/Container.h
src/ContainerInfo.cpp
src/ContainerInfo.h
src/GSException.h
src/PartitionController.cpp
src/PartitionController.h
src/Query.cpp
src/Query.h
src/Resource.cpp
src/Resource.h
src/Row.cpp
src/Row.h
src/RowKeyPredicate.cpp
src/RowKeyPredicate.h
src/RowSet.cpp
src/RowSet.h
src/Store.cpp
src/Store.h
src/StoreFactory.cpp
src/StoreFactory.h
src/Timestamp.cpp
src/Timestamp.h
src/griddb.i
src/gstype.i
src/gstype_python.i