Metadata-Version: 1.1
Name: griddb-python-client
Version: 0.5.2
Summary: GridDB Python Client Library built using SWIG
Home-page: https://github.com/griddb/griddb_client
Author: Katsuhiko Nonomura
Author-email: contact@griddb.org
License: Apache Software License
Platform: UNKNOWN
Classifier: License :: OSI Approved :: Apache Software License
Classifier: Operating System :: POSIX :: Linux
Classifier: Programming Language :: Python
Classifier: Programming Language :: Python :: 2
Classifier: Programming Language :: Python :: 2.6
Classifier: Programming Language :: Python :: 3
Classifier: Programming Language :: Python :: 3.6
